{
  "Server":{
    "SystemConfig":{
      "IrmcConfig":{
        "NetworkServices":{
          "Snmp":{
            "TrapDestinations":{
              "TrapDestination":[
                {
                  "@TrapDestinationIdx":0,
                  "Name":"10.172.124.18",
                  "Protocol":"SnmpV1"
                },
                {
                  "@TrapDestinationIdx":1,
                  "Name":"10.172.125.138",
                  "Protocol":"SnmpV1"
                },
                {
                  "@TrapDestinationIdx":2,
                  "Name":"",
                  "Protocol":"SnmpV1"
                },
                {
                  "@TrapDestinationIdx":3,
                  "Name":"",
                  "Protocol":"SnmpV1"
                },
                {
                  "@TrapDestinationIdx":4,
                  "Name":"",
                  "Protocol":"SnmpV1"
                },
                {
                  "@TrapDestinationIdx":5,
                  "Name":"",
                  "Protocol":"SnmpV1"
                },
                {
                  "@TrapDestinationIdx":6,
                  "Name":"",
                  "Protocol":"SnmpV1"
                }
              ]
            },
            "SnmpV3":{
              "TrapUserIndex":0,
              "EngineID":"800000e7034c5262495db8"
            },
            "TrapCommunityName":"public",
            "ServicePort":161,
            "Enabled":false,
            "CommunityName":"public",
            "ServiceVersion":"All",
            "PagingEnabled":false
          }
        },
        "@Version":"1.07"
      }
    },
    "@Version":"1.01"
  }
}